{
  "parent": "minecraft:recipes/root",
  "criteria": {
    "has_avrillium_ingot": {
      "conditions": {
        "items": [
          {
            "items": [
              "earthguard:avrillium_ingot"
            ]
          }
        ]
      },
      "trigger": "minecraft:inventory_changed"
    },
    "has_steel_helmet": {
      "conditions": {
        "items": [
          {
            "items": [
              "earthguard:steel_helmet"
            ]
          }
        ]
      },
      "trigger": "minecraft:inventory_changed"
    },
    "has_the_recipe": {
      "conditions": {
        "recipe": "minecraft:avrillium_helmet"
      },
      "trigger": "minecraft:recipe_unlocked"
    }
  },
  "requirements": [
    [
      "has_steel_helmet",
      "has_avrillium_ingot",
      "has_the_recipe"
    ]
  ],
  "rewards": {
    "recipes": [
      "minecraft:avrillium_helmet"
    ]
  }
}